migrations/__init__.py
migrations/env.py
sei_seeker_models/__init__.py
sei_seeker_models/base.py
sei_seeker_models/collection.py
sei_seeker_models/floor.py
sei_seeker_models/listing.py
sei_seeker_models/mint.py
sei_seeker_models/sales.py
sei_seeker_models/snipe_job.py
sei_seeker_models/tg_user.py
sei_seeker_models/transaction.py
sei_seeker_models/volume.py
sei_seeker_models-9.0.0.dist-info/METADATA
sei_seeker_models-9.0.0.dist-info/WHEEL
sei_seeker_models-9.0.0.dist-info/top_level.txt
sei_seeker_models-9.0.0.dist-info/RECORD
