Metadata-Version: 2.1
Name: sei-seeker-models
Version: 9.0.0
Summary: HYPERLABS
Home-page: UNKNOWN
License: UNKNOWN
Platform: UNKNOWN
Requires-Python: >=3.9
Requires-Dist: psycopg2-binary ==2.9.9
Requires-Dist: SQLAlchemy ==2.0.27
